httpx_spy/__init__.py
httpx_spy/moesif.py
httpx_spy/monkey.py
httpx_spy/processor.py
httpx_spy/uniqueue.py
httpx_spy/django/__init__.py
httpx_spy/django/apps.py
httpx_spy/django/common.py
httpx_spy/django/tasks.py
httpx_spy-0.1.2.dist-info/METADATA
httpx_spy-0.1.2.dist-info/WHEEL
httpx_spy-0.1.2.dist-info/RECORD
